{
  "Room": [
    {
      "id": 1,
      "title": "Entrance Hall",
      "description": "The main entrance to the building, with a grand staircase leading up.",
      "left": 2,
      "right": 3
    },
    {
      "id": 2,
      "title": "Library",
      "description": "A quiet room filled with shelves of books and comfortable reading chairs.",
      "left": 4,
      "right": 1
    },
    {
      "id": 3,
      "title": "Dining Room",
      "description": "A large room with a long dining table and ornate decorations.",
      "left": 1,
      "right": 5
    },
    {
      "id": 4,
      "title": "Study",
      "description": "A small room with a desk, computer, and various office supplies.",
      "left": null,
      "right": 2
    },
    {
      "id": 5,
      "title": "Kitchen",
      "description": "A modern kitchen with all the latest appliances and a large island in the center.",
      "left": 3,
      "right": null
    }
  ],
  "Dungeon": [
  {
    "id": 1,
    "title": "Entrance",
    "description": "The main entrance to the dungeon.",
    "type": "Entrance",
    "left_id": null,
    "right_id": 2,
    "front_id": 5,
    "rear_id": null,
    "top_id": 17,
    "down_id": null,
    "coord_x": 0,
    "coord_y": 0,
    "coord_z": 0
  },
  {
    "id": 2,
    "title": "Hidden Room",
    "description": "A echoing with distant sounds.",
    "type": "Monster",
    "left_id": 1,
    "right_id": 3,
    "front_id": 6,
    "rear_id": null,
    "top_id": null,
    "down_id": null,
    "coord_x": 1,
    "coord_y": 0,
    "coord_z": 0
  },
  {
    "id": 3,
    "title": "Mysterious Room",
    "description": "A filled with cobwebs.",
    "type": "Hallway",
    "left_id": 2,
    "right_id": 4,
    "front_id": 7,
    "rear_id": null,
    "top_id": null,
    "down_id": null,
    "coord_x": 2,
    "coord_y": 0,
    "coord_z": 0
  },
  {
    "id": 4,
    "title": "Mysterious Room",
    "description": "A covered in dust.",
    "type": "Monster",
    "left_id": 3,
    "right_id": null,
    "front_id": 8,
    "rear_id": null,
    "top_id": null,
    "down_id": null,
    "coord_x": 3,
    "coord_y": 0,
    "coord_z": 0
  },
  {
    "id": 5,
    "title": "Forgotten Room",
    "description": "A lit by flickering torches.",
    "type": "Treasure",
    "left_id": null,
    "right_id": 6,
    "front_id": 9,
    "rear_id": 1,
    "top_id": null,
    "down_id": null,
    "coord_x": 0,
    "coord_y": 1,
    "coord_z": 0
  },
  {
    "id": 6,
    "title": "Mysterious Room",
    "description": "A echoing with distant sounds.",
    "type": "Final",
    "left_id": 5,
    "right_id": 7,
    "front_id": 10,
    "rear_id": 2,
    "top_id": null,
    "down_id": null,
    "coord_x": 1,
    "coord_y": 1,
    "coord_z": 0
  },
  {
    "id": 7,
    "title": "Forgotten Room",
    "description": "A with walls covered in ancient runes.",
    "type": "Monster",
    "left_id": 6,
    "right_id": 8,
    "front_id": 11,
    "rear_id": 3,
    "top_id": null,
    "down_id": null,
    "coord_x": 2,
    "coord_y": 1,
    "coord_z": 0
  },
  {
    "id": 8,
    "title": "Forgotten Room",
    "description": "A echoing with distant sounds.",
    "type": "Treasure",
    "left_id": 7,
    "right_id": null,
    "front_id": 12,
    "rear_id": 4,
    "top_id": null,
    "down_id": null,
    "coord_x": 3,
    "coord_y": 1,
    "coord_z": 0
  },
  {
    "id": 9,
    "title": "Forgotten Room",
    "description": "A lit by flickering torches.",
    "type": "Puzzle",
    "left_id": null,
    "right_id": 10,
    "front_id": 13,
    "rear_id": 5,
    "top_id": null,
    "down_id": null,
    "coord_x": 0,
    "coord_y": 2,
    "coord_z": 0
  },
  {
    "id": 10,
    "title": "Hidden Room",
    "description": "A with walls covered in ancient runes.",
    "type": "Puzzle",
    "left_id": 9,
    "right_id": 11,
    "front_id": 14,
    "rear_id": 6,
    "top_id": null,
    "down_id": null,
    "coord_x": 1,
    "coord_y": 2,
    "coord_z": 0
  },
  {
    "id": 11,
    "title": "Ancient Room",
    "description": "A lit by flickering torches.",
    "type": "Treasure",
    "left_id": 10,
    "right_id": 12,
    "front_id": 15,
    "rear_id": 7,
    "top_id": null,
    "down_id": null,
    "coord_x": 2,
    "coord_y": 2,
    "coord_z": 0
  },
  {
    "id": 12,
    "title": "Ancient Room",
    "description": "A with walls covered in ancient runes.",
    "type": "Monster",
    "left_id": 11,
    "right_id": null,
    "front_id": 16,
    "rear_id": 8,
    "top_id": null,
    "down_id": null,
    "coord_x": 3,
    "coord_y": 2,
    "coord_z": 0
  },
  {
    "id": 13,
    "title": "Hidden Room",
    "description": "A covered in dust.",
    "type": "Final",
    "left_id": null,
    "right_id": 14,
    "front_id": null,
    "rear_id": 9,
    "top_id": null,
    "down_id": null,
    "coord_x": 0,
    "coord_y": 3,
    "coord_z": 0
  },
  {
    "id": 14,
    "title": "Forgotten Room",
    "description": "A covered in dust.",
    "type": "Puzzle",
    "left_id": 13,
    "right_id": 15,
    "front_id": null,
    "rear_id": 10,
    "top_id": null,
    "down_id": null,
    "coord_x": 1,
    "coord_y": 3,
    "coord_z": 0
  },
  {
    "id": 15,
    "title": "Forgotten Room",
    "description": "A covered in dust.",
    "type": "Hallway",
    "left_id": 14,
    "right_id": 16,
    "front_id": null,
    "rear_id": 11,
    "top_id": null,
    "down_id": null,
    "coord_x": 2,
    "coord_y": 3,
    "coord_z": 0
  },
  {
    "id": 16,
    "title": "Hidden Room",
    "description": "A with walls covered in ancient runes.",
    "type": "Final",
    "left_id": 15,
    "right_id": null,
    "front_id": null,
    "rear_id": 12,
    "top_id": null,
    "down_id": null,
    "coord_x": 3,
    "coord_y": 3,
    "coord_z": 0
  },
  {
    "id": 17,
    "title": "Hidden Room",
    "description": "A echoing with distant sounds.",
    "type": "Final",
    "left_id": null,
    "right_id": 18,
    "front_id": 21,
    "rear_id": null,
    "top_id": null,
    "down_id": 1,
    "coord_x": 0,
    "coord_y": 0,
    "coord_z": 1
  },
  {
    "id": 18,
    "title": "Mysterious Room",
    "description": "A filled with cobwebs.",
    "type": "Monster",
    "left_id": 17,
    "right_id": 19,
    "front_id": 22,
    "rear_id": null,
    "top_id": null,
    "down_id": null,
    "coord_x": 1,
    "coord_y": 0,
    "coord_z": 1
  },
  {
    "id": 19,
    "title": "Forgotten Room",
    "description": "A filled with cobwebs.",
    "type": "Hallway",
    "left_id": 18,
    "right_id": 20,
    "front_id": 23,
    "rear_id": null,
    "top_id": null,
    "down_id": null,
    "coord_x": 2,
    "coord_y": 0,
    "coord_z": 1
  },
  {
    "id": 20,
    "title": "Hidden Room",
    "description": "A covered in dust.",
    "type": "Final",
    "left_id": 19,
    "right_id": null,
    "front_id": 24,
    "rear_id": null,
    "top_id": null,
    "down_id": null,
    "coord_x": 3,
    "coord_y": 0,
    "coord_z": 1
  },
  {
    "id": 21,
    "title": "Mysterious Room",
    "description": "A covered in dust.",
    "type": "Final",
    "left_id": null,
    "right_id": 22,
    "front_id": 25,
    "rear_id": 17,
    "top_id": null,
    "down_id": null,
    "coord_x": 0,
    "coord_y": 1,
    "coord_z": 1
  },
  {
    "id": 22,
    "title": "Dark Room",
    "description": "A echoing with distant sounds.",
    "type": "Monster",
    "left_id": 21,
    "right_id": 23,
    "front_id": 26,
    "rear_id": 18,
    "top_id": null,
    "down_id": null,
    "coord_x": 1,
    "coord_y": 1,
    "coord_z": 1
  },
  {
    "id": 23,
    "title": "Hidden Room",
    "description": "A with walls covered in ancient runes.",
    "type": "Puzzle",
    "left_id": 22,
    "right_id": 24,
    "front_id": 27,
    "rear_id": 19,
    "top_id": null,
    "down_id": null,
    "coord_x": 2,
    "coord_y": 1,
    "coord_z": 1
  },
  {
    "id": 24,
    "title": "Hidden Room",
    "description": "A filled with cobwebs.",
    "type": "Final",
    "left_id": 23,
    "right_id": null,
    "front_id": 28,
    "rear_id": 20,
    "top_id": null,
    "down_id": null,
    "coord_x": 3,
    "coord_y": 1,
    "coord_z": 1
  },
  {
    "id": 25,
    "title": "Hidden Room",
    "description": "A with walls covered in ancient runes.",
    "type": "Monster",
    "left_id": null,
    "right_id": 26,
    "front_id": 29,
    "rear_id": 21,
    "top_id": null,
    "down_id": null,
    "coord_x": 0,
    "coord_y": 2,
    "coord_z": 1
  },
  {
    "id": 26,
    "title": "Hidden Room",
    "description": "A echoing with distant sounds.",
    "type": "Final",
    "left_id": 25,
    "right_id": 27,
    "front_id": 30,
    "rear_id": 22,
    "top_id": null,
    "down_id": null,
    "coord_x": 1,
    "coord_y": 2,
    "coord_z": 1
  },
  {
    "id": 27,
    "title": "Forgotten Room",
    "description": "A covered in dust.",
    "type": "Treasure",
    "left_id": 26,
    "right_id": 28,
    "front_id": 31,
    "rear_id": 23,
    "top_id": null,
    "down_id": null,
    "coord_x": 2,
    "coord_y": 2,
    "coord_z": 1
  },
  {
    "id": 28,
    "title": "Hidden Room",
    "description": "A echoing with distant sounds.",
    "type": "Treasure",
    "left_id": 27,
    "right_id": null,
    "front_id": 32,
    "rear_id": 24,
    "top_id": null,
    "down_id": null,
    "coord_x": 3,
    "coord_y": 2,
    "coord_z": 1
  },
  {
    "id": 29,
    "title": "Dark Room",
    "description": "A filled with cobwebs.",
    "type": "Hallway",
    "left_id": null,
    "right_id": 30,
    "front_id": null,
    "rear_id": 25,
    "top_id": null,
    "down_id": null,
    "coord_x": 0,
    "coord_y": 3,
    "coord_z": 1
  },
  {
    "id": 30,
    "title": "Forgotten Room",
    "description": "A filled with cobwebs.",
    "type": "Treasure",
    "left_id": 29,
    "right_id": 31,
    "front_id": null,
    "rear_id": 26,
    "top_id": null,
    "down_id": null,
    "coord_x": 1,
    "coord_y": 3,
    "coord_z": 1
  },
  {
    "id": 31,
    "title": "Mysterious Room",
    "description": "A echoing with distant sounds.",
    "type": "Treasure",
    "left_id": 30,
    "right_id": 32,
    "front_id": null,
    "rear_id": 27,
    "top_id": null,
    "down_id": null,
    "coord_x": 2,
    "coord_y": 3,
    "coord_z": 1
  },
  {
    "id": 32,
    "title": "Dark Room",
    "description": "A covered in dust.",
    "type": "Monster",
    "left_id": 31,
    "right_id": null,
    "front_id": null,
    "rear_id": 28,
    "top_id": null,
    "down_id": null,
    "coord_x": 3,
    "coord_y": 3,
    "coord_z": 1
  },
  {
    "id": 33,
    "title": "Ancient Room",
    "description": "A covered in dust.",
    "type": "Treasure",
    "left_id": null,
    "right_id": 34,
    "front_id": 37,
    "rear_id": null,
    "top_id": null,
    "down_id": null,
    "coord_x": 0,
    "coord_y": 0,
    "coord_z": 2
  },
  {
    "id": 34,
    "title": "Hidden Room",
    "description": "A with walls covered in ancient runes.",
    "type": "Puzzle",
    "left_id": 33,
    "right_id": 35,
    "front_id": 38,
    "rear_id": null,
    "top_id": null,
    "down_id": null,
    "coord_x": 1,
    "coord_y": 0,
    "coord_z": 2
  },
  {
    "id": 35,
    "title": "Dark Room",
    "description": "A lit by flickering torches.",
    "type": "Puzzle",
    "left_id": 34,
    "right_id": 36,
    "front_id": 39,
    "rear_id": null,
    "top_id": null,
    "down_id": null,
    "coord_x": 2,
    "coord_y": 0,
    "coord_z": 2
  },
  {
    "id": 36,
    "title": "Dark Room",
    "description": "A echoing with distant sounds.",
    "type": "Treasure",
    "left_id": 35,
    "right_id": null,
    "front_id": 40,
    "rear_id": null,
    "top_id": null,
    "down_id": null,
    "coord_x": 3,
    "coord_y": 0,
    "coord_z": 2
  },
  {
    "id": 37,
    "title": "Mysterious Room",
    "description": "A echoing with distant sounds.",
    "type": "Final",
    "left_id": null,
    "right_id": 38,
    "front_id": 41,
    "rear_id": 33,
    "top_id": null,
    "down_id": null,
    "coord_x": 0,
    "coord_y": 1,
    "coord_z": 2
  },
  {
    "id": 38,
    "title": "Hidden Room",
    "description": "A with walls covered in ancient runes.",
    "type": "Hallway",
    "left_id": 37,
    "right_id": 39,
    "front_id": 42,
    "rear_id": 34,
    "top_id": null,
    "down_id": null,
    "coord_x": 1,
    "coord_y": 1,
    "coord_z": 2
  },
  {
    "id": 39,
    "title": "Hidden Room",
    "description": "A lit by flickering torches.",
    "type": "Puzzle",
    "left_id": 38,
    "right_id": 40,
    "front_id": 43,
    "rear_id": 35,
    "top_id": null,
    "down_id": null,
    "coord_x": 2,
    "coord_y": 1,
    "coord_z": 2
  },
  {
    "id": 40,
    "title": "Ancient Room",
    "description": "A covered in dust.",
    "type": "Final",
    "left_id": 39,
    "right_id": null,
    "front_id": 44,
    "rear_id": 36,
    "top_id": null,
    "down_id": null,
    "coord_x": 3,
    "coord_y": 1,
    "coord_z": 2
  },
  {
    "id": 41,
    "title": "Hidden Room",
    "description": "A echoing with distant sounds.",
    "type": "Final",
    "left_id": null,
    "right_id": 42,
    "front_id": 45,
    "rear_id": 37,
    "top_id": null,
    "down_id": null,
    "coord_x": 0,
    "coord_y": 2,
    "coord_z": 2
  },
  {
    "id": 42,
    "title": "Mysterious Room",
    "description": "A filled with cobwebs.",
    "type": "Monster",
    "left_id": 41,
    "right_id": 43,
    "front_id": 46,
    "rear_id": 38,
    "top_id": null,
    "down_id": null,
    "coord_x": 1,
    "coord_y": 2,
    "coord_z": 2
  },
  {
    "id": 43,
    "title": "Mysterious Room",
    "description": "A filled with cobwebs.",
    "type": "Treasure",
    "left_id": 42,
    "right_id": 44,
    "front_id": 47,
    "rear_id": 39,
    "top_id": null,
    "down_id": null,
    "coord_x": 2,
    "coord_y": 2,
    "coord_z": 2
  },
  {
    "id": 44,
    "title": "Ancient Room",
    "description": "A echoing with distant sounds.",
    "type": "Monster",
    "left_id": 43,
    "right_id": null,
    "front_id": 48,
    "rear_id": 40,
    "top_id": null,
    "down_id": null,
    "coord_x": 3,
    "coord_y": 2,
    "coord_z": 2
  },
  {
    "id": 45,
    "title": "Dark Room",
    "description": "A echoing with distant sounds.",
    "type": "Hallway",
    "left_id": null,
    "right_id": 46,
    "front_id": null,
    "rear_id": 41,
    "top_id": null,
    "down_id": null,
    "coord_x": 0,
    "coord_y": 3,
    "coord_z": 2
  },
  {
    "id": 46,
    "title": "Hidden Room",
    "description": "A lit by flickering torches.",
    "type": "Puzzle",
    "left_id": 45,
    "right_id": 47,
    "front_id": null,
    "rear_id": 42,
    "top_id": null,
    "down_id": null,
    "coord_x": 1,
    "coord_y": 3,
    "coord_z": 2
  },
  {
    "id": 47,
    "title": "Forgotten Room",
    "description": "A with walls covered in ancient runes.",
    "type": "Hallway",
    "left_id": 46,
    "right_id": 48,
    "front_id": null,
    "rear_id": 43,
    "top_id": null,
    "down_id": null,
    "coord_x": 2,
    "coord_y": 3,
    "coord_z": 2
  },
  {
    "id": 48,
    "title": "Dark Room",
    "description": "A filled with cobwebs.",
    "type": "Hallway",
    "left_id": 47,
    "right_id": null,
    "front_id": null,
    "rear_id": 44,
    "top_id": 64,
    "down_id": null,
    "coord_x": 3,
    "coord_y": 3,
    "coord_z": 2
  },
  {
    "id": 49,
    "title": "Mysterious Room",
    "description": "A lit by flickering torches.",
    "type": "Monster",
    "left_id": null,
    "right_id": 50,
    "front_id": 53,
    "rear_id": null,
    "top_id": null,
    "down_id": null,
    "coord_x": 0,
    "coord_y": 0,
    "coord_z": 3
  },
  {
    "id": 50,
    "title": "Mysterious Room",
    "description": "A covered in dust.",
    "type": "Puzzle",
    "left_id": 49,
    "right_id": 51,
    "front_id": 54,
    "rear_id": null,
    "top_id": null,
    "down_id": null,
    "coord_x": 1,
    "coord_y": 0,
    "coord_z": 3
  },
  {
    "id": 51,
    "title": "Ancient Room",
    "description": "A with walls covered in ancient runes.",
    "type": "Treasure",
    "left_id": 50,
    "right_id": 52,
    "front_id": 55,
    "rear_id": null,
    "top_id": null,
    "down_id": null,
    "coord_x": 2,
    "coord_y": 0,
    "coord_z": 3
  },
  {
    "id": 52,
    "title": "Dark Room",
    "description": "A lit by flickering torches.",
    "type": "Final",
    "left_id": 51,
    "right_id": null,
    "front_id": 56,
    "rear_id": null,
    "top_id": null,
    "down_id": null,
    "coord_x": 3,
    "coord_y": 0,
    "coord_z": 3
  },
  {
    "id": 53,
    "title": "Ancient Room",
    "description": "A with walls covered in ancient runes.",
    "type": "Monster",
    "left_id": null,
    "right_id": 54,
    "front_id": 57,
    "rear_id": 49,
    "top_id": null,
    "down_id": null,
    "coord_x": 0,
    "coord_y": 1,
    "coord_z": 3
  },
  {
    "id": 54,
    "title": "Dark Room",
    "description": "A lit by flickering torches.",
    "type": "Treasure",
    "left_id": 53,
    "right_id": 55,
    "front_id": 58,
    "rear_id": 50,
    "top_id": null,
    "down_id": null,
    "coord_x": 1,
    "coord_y": 1,
    "coord_z": 3
  },
  {
    "id": 55,
    "title": "Ancient Room",
    "description": "A lit by flickering torches.",
    "type": "Monster",
    "left_id": 54,
    "right_id": 56,
    "front_id": 59,
    "rear_id": 51,
    "top_id": null,
    "down_id": null,
    "coord_x": 2,
    "coord_y": 1,
    "coord_z": 3
  },
  {
    "id": 56,
    "title": "Mysterious Room",
    "description": "A with walls covered in ancient runes.",
    "type": "Puzzle",
    "left_id": 55,
    "right_id": null,
    "front_id": 60,
    "rear_id": 52,
    "top_id": null,
    "down_id": null,
    "coord_x": 3,
    "coord_y": 1,
    "coord_z": 3
  },
  {
    "id": 57,
    "title": "Forgotten Room",
    "description": "A with walls covered in ancient runes.",
    "type": "Treasure",
    "left_id": null,
    "right_id": 58,
    "front_id": 61,
    "rear_id": 53,
    "top_id": null,
    "down_id": null,
    "coord_x": 0,
    "coord_y": 2,
    "coord_z": 3
  },
  {
    "id": 58,
    "title": "Forgotten Room",
    "description": "A echoing with distant sounds.",
    "type": "Treasure",
    "left_id": 57,
    "right_id": 59,
    "front_id": 62,
    "rear_id": 54,
    "top_id": null,
    "down_id": null,
    "coord_x": 1,
    "coord_y": 2,
    "coord_z": 3
  },
  {
    "id": 59,
    "title": "Hidden Room",
    "description": "A covered in dust.",
    "type": "Monster",
    "left_id": 58,
    "right_id": 60,
    "front_id": 63,
    "rear_id": 55,
    "top_id": null,
    "down_id": null,
    "coord_x": 2,
    "coord_y": 2,
    "coord_z": 3
  },
  {
    "id": 60,
    "title": "Dark Room",
    "description": "A lit by flickering torches.",
    "type": "Final",
    "left_id": 59,
    "right_id": null,
    "front_id": 64,
    "rear_id": 56,
    "top_id": null,
    "down_id": null,
    "coord_x": 3,
    "coord_y": 2,
    "coord_z": 3
  },
  {
    "id": 61,
    "title": "Dark Room",
    "description": "A filled with cobwebs.",
    "type": "Monster",
    "left_id": null,
    "right_id": 62,
    "front_id": null,
    "rear_id": 57,
    "top_id": null,
    "down_id": null,
    "coord_x": 0,
    "coord_y": 3,
    "coord_z": 3
  },
  {
    "id": 62,
    "title": "Ancient Room",
    "description": "A lit by flickering torches.",
    "type": "Puzzle",
    "left_id": 61,
    "right_id": 63,
    "front_id": null,
    "rear_id": 58,
    "top_id": null,
    "down_id": null,
    "coord_x": 1,
    "coord_y": 3,
    "coord_z": 3
  },
  {
    "id": 63,
    "title": "Dark Room",
    "description": "A covered in dust.",
    "type": "Final",
    "left_id": 62,
    "right_id": 64,
    "front_id": null,
    "rear_id": 59,
    "top_id": null,
    "down_id": null,
    "coord_x": 2,
    "coord_y": 3,
    "coord_z": 3
  },
  {
    "id": 64,
    "title": "Final Room",
    "description": "The final room of the dungeon.",
    "type": "Final",
    "left_id": 63,
    "right_id": null,
    "front_id": null,
    "rear_id": 60,
    "top_id": null,
    "down_id": 48,
    "coord_x": 3,
    "coord_y": 3,
    "coord_z": 3
  }
],
  "Monster": [
    {
      "id": 1,
      "name": "Ferocious Dragon",
      "description": "A mighty dragon with immense power and a fearsome reputation.",
      "attack": 86,
      "defense": 86,
      "hitpoints": 663,
      "tier": "Legendary"
    },
    {
      "id": 2,
      "name": "Ferocious Goblin",
      "description": "A beast that lurks in the shadows, waiting for its next victim.",
      "attack": 38,
      "defense": 31,
      "hitpoints": 413,
      "tier": "Legendary"
    },
    {
      "id": 3,
      "name": "Savage Goblin",
      "description": "A terrifying entity that haunts the darkest corners of the world.",
      "attack": 67,
      "defense": 67,
      "hitpoints": 557,
      "tier": "Legendary"
    },
    {
      "id": 4,
      "name": "Ferocious Demon",
      "description": "A beast that lurks in the shadows, waiting for its next victim.",
      "attack": 18,
      "defense": 10,
      "hitpoints": 141,
      "tier": "Rare"
    },
    {
      "id": 5,
      "name": "Dark Troll",
      "description": "A monster known for its cunning and brutality.",
      "attack": 18,
      "defense": 16,
      "hitpoints": 190,
      "tier": "Rare"
    },
    {
      "id": 6,
      "name": "Ferocious Golem",
      "description": "A fearsome foe with a reputation for savagery.",
      "attack": 20,
      "defense": 16,
      "hitpoints": 132,
      "tier": "Rare"
    },
    {
      "id": 7,
      "name": "Dark Golem",
      "description": "A creature that strikes fear into the hearts of all who encounter it.",
      "attack": 13,
      "defense": 12,
      "hitpoints": 163,
      "tier": "Rare"
    },
    {
      "id": 8,
      "name": "Brutal Skeleton",
      "description": "A creature that strikes fear into the hearts of all who encounter it.",
      "attack": 17,
      "defense": 17,
      "hitpoints": 155,
      "tier": "Rare"
    },
    {
      "id": 9,
      "name": "Brutal Orc",
      "description": "A terrifying entity that haunts the darkest corners of the world.",
      "attack": 19,
      "defense": 15,
      "hitpoints": 182,
      "tier": "Rare"
    },
    {
      "id": 10,
      "name": "Mysterious Zombie",
      "description": "A fearsome foe with a reputation for savagery.",
      "attack": 14,
      "defense": 19,
      "hitpoints": 173,
      "tier": "Rare"
    },
    {
      "id": 11,
      "name": "Cunning Golem",
      "description": "A monster known for its cunning and brutality.",
      "attack": 17,
      "defense": 15,
      "hitpoints": 133,
      "tier": "Rare"
    },
    {
      "id": 12,
      "name": "Ferocious Witch",
      "description": "A terrifying entity that haunts the darkest corners of the world.",
      "attack": 12,
      "defense": 14,
      "hitpoints": 113,
      "tier": "Rare"
    },
    {
      "id": 13,
      "name": "Brutal Zombie",
      "description": "A fearsome foe with a reputation for savagery.",
      "attack": 11,
      "defense": 14,
      "hitpoints": 196,
      "tier": "Rare"
    },
    {
      "id": 14,
      "name": "Sinister Golem",
      "description": "A beast that lurks in the shadows, waiting for its next victim.",
      "attack": 17,
      "defense": 14,
      "hitpoints": 172,
      "tier": "Rare"
    },
    {
      "id": 15,
      "name": "Vicious Witch",
      "description": "A beast that lurks in the shadows, waiting for its next victim.",
      "attack": 20,
      "defense": 15,
      "hitpoints": 140,
      "tier": "Rare"
    },
    {
      "id": 16,
      "name": "Mysterious Skeleton",
      "description": "A beast that lurks in the shadows, waiting for its next victim.",
      "attack": 3,
      "defense": 3,
      "hitpoints": 36,
      "tier": "Common"
    },
    {
      "id": 17,
      "name": "Vicious Troll",
      "description": "A monster known for its cunning and brutality.",
      "attack": 4,
      "defense": 3,
      "hitpoints": 79,
      "tier": "Common"
    },
    {
      "id": 18,
      "name": "Savage Witch",
      "description": "A fearsome foe with a reputation for savagery.",
      "attack": 10,
      "defense": 2,
      "hitpoints": 64,
      "tier": "Common"
    },
    {
      "id": 19,
      "name": "Brutal Dragon",
      "description": "A fearsome foe with a reputation for savagery.",
      "attack": 2,
      "defense": 10,
      "hitpoints": 15,
      "tier": "Common"
    },
    {
      "id": 20,
      "name": "Sinister Vampire",
      "description": "A terrifying entity that haunts the darkest corners of the world.",
      "attack": 6,
      "defense": 8,
      "hitpoints": 48,
      "tier": "Common"
    },
    {
      "id": 21,
      "name": "Ancient Orc",
      "description": "A monster known for its cunning and brutality.",
      "attack": 3,
      "defense": 9,
      "hitpoints": 24,
      "tier": "Common"
    },
    {
      "id": 22,
      "name": "Vicious Zombie",
      "description": "A beast that lurks in the shadows, waiting for its next victim.",
      "attack": 9,
      "defense": 2,
      "hitpoints": 42,
      "tier": "Common"
    },
    {
      "id": 23,
      "name": "Sinister Goblin",
      "description": "A monster known for its cunning and brutality.",
      "attack": 8,
      "defense": 2,
      "hitpoints": 59,
      "tier": "Common"
    },
    {
      "id": 24,
      "name": "Sinister Zombie",
      "description": "A creature that strikes fear into the hearts of all who encounter it.",
      "attack": 4,
      "defense": 2,
      "hitpoints": 24,
      "tier": "Common"
    },
    {
      "id": 25,
      "name": "Vicious Goblin",
      "description": "A monster known for its cunning and brutality.",
      "attack": 2,
      "defense": 2,
      "hitpoints": 33,
      "tier": "Common"
    },
    {
      "id": 26,
      "name": "Dark Witch",
      "description": "A monster known for its cunning and brutality.",
      "attack": 5,
      "defense": 3,
      "hitpoints": 100,
      "tier": "Common"
    },
    {
      "id": 27,
      "name": "Mysterious Dragon",
      "description": "A terrifying entity that haunts the darkest corners of the world.",
      "attack": 10,
      "defense": 4,
      "hitpoints": 59,
      "tier": "Common"
    },
    {
      "id": 28,
      "name": "Sinister Orc",
      "description": "A monster known for its cunning and brutality.",
      "attack": 1,
      "defense": 3,
      "hitpoints": 53,
      "tier": "Common"
    },
    {
      "id": 29,
      "name": "Malevolent Vampire",
      "description": "A terrifying entity that haunts the darkest corners of the world.",
      "attack": 4,
      "defense": 5,
      "hitpoints": 83,
      "tier": "Common"
    },
    {
      "id": 30,
      "name": "Vicious Vampire",
      "description": "A beast that lurks in the shadows, waiting for its next victim.",
      "attack": 6,
      "defense": 6,
      "hitpoints": 92,
      "tier": "Common"
    },
    {
      "id": 31,
      "name": "Malevolent Witch",
      "description": "A fearsome foe with a reputation for savagery.",
      "attack": 8,
      "defense": 9,
      "hitpoints": 15,
      "tier": "Common"
    },
    {
      "id": 32,
      "name": "Brutal Witch",
      "description": "A fearsome foe with a reputation for savagery.",
      "attack": 7,
      "defense": 6,
      "hitpoints": 39,
      "tier": "Common"
    },
    {
      "id": 33,
      "name": "Ferocious Zombie",
      "description": "A terrifying entity that haunts the darkest corners of the world.",
      "attack": 8,
      "defense": 1,
      "hitpoints": 89,
      "tier": "Common"
    },
    {
      "id": 34,
      "name": "Cunning Vampire",
      "description": "A terrifying entity that haunts the darkest corners of the world.",
      "attack": 5,
      "defense": 9,
      "hitpoints": 59,
      "tier": "Common"
    },
    {
      "id": 35,
      "name": "Mysterious Witch",
      "description": "A beast that lurks in the shadows, waiting for its next victim.",
      "attack": 5,
      "defense": 10,
      "hitpoints": 50,
      "tier": "Common"
    },
    {
      "id": 36,
      "name": "Brutal Goblin",
      "description": "A monster known for its cunning and brutality.",
      "attack": 3,
      "defense": 7,
      "hitpoints": 86,
      "tier": "Common"
    },
    {
      "id": 37,
      "name": "Brutal Vampire",
      "description": "A terrifying entity that haunts the darkest corners of the world.",
      "attack": 2,
      "defense": 6,
      "hitpoints": 12,
      "tier": "Common"
    },
    {
      "id": 38,
      "name": "Sinister Demon",
      "description": "A monster known for its cunning and brutality.",
      "attack": 3,
      "defense": 9,
      "hitpoints": 82,
      "tier": "Common"
    },
    {
      "id": 39,
      "name": "Dark Dragon",
      "description": "A creature that strikes fear into the hearts of all who encounter it.",
      "attack": 7,
      "defense": 7,
      "hitpoints": 24,
      "tier": "Common"
    },
    {
      "id": 40,
      "name": "Ancient Witch",
      "description": "A creature that strikes fear into the hearts of all who encounter it.",
      "attack": 4,
      "defense": 10,
      "hitpoints": 47,
      "tier": "Common"
    }
  ]
}